govyn/__init__.py
govyn/app.py
govyn/auth.py
govyn/endpoint.py
govyn/errors.py
govyn/metrics.py
govyn/openapi.py
govyn/py.typed
govyn/route_def.py
govyn/schemas.py
govyn/security.py
govyn-0.19.0.dist-info/METADATA
govyn-0.19.0.dist-info/WHEEL
govyn-0.19.0.dist-info/top_level.txt
govyn-0.19.0.dist-info/RECORD
